ai_artist/__init__.py
ai_artist/image_generator.py
ai_artist/util.py
ai_artist-0.0.2.dist-info/LICENSE
ai_artist-0.0.2.dist-info/METADATA
ai_artist-0.0.2.dist-info/WHEEL
ai_artist-0.0.2.dist-info/top_level.txt
ai_artist-0.0.2.dist-info/RECORD
