Metadata-Version: 2.1
Name: ai-artist
Version: 0.0.2
Summary: ai_artist made generating image easy using Stable Diffusion AI model.
Home-page: https://github.com/thinh-vu/ai_artist
Author: Thinh Vu
Author-email: mrthinh@live.com
Classifier: Programming Language :: Python :: 3
Classifier: License :: OSI Approved :: MIT License
Classifier: Operating System :: OS Independent
Requires-Python: >=3.7
License-File: LICENSE
Requires-Dist: diffusers
Requires-Dist: transformers
Requires-Dist: scipy
Requires-Dist: ftfy
Requires-Dist: accelerate
